pdum/__init__.py
pdum/criu/__init__.py
pdum/criu/cli.py
pdum/criu/py.typed
pdum/criu/utils.py
pdum/criu/goblins/__init__.py
habemus_papadum_criu-0.7.0.dist-info/METADATA
habemus_papadum_criu-0.7.0.dist-info/WHEEL
habemus_papadum_criu-0.7.0.dist-info/entry_points.txt
habemus_papadum_criu-0.7.0.dist-info/licenses/LICENSE
habemus_papadum_criu-0.7.0.dist-info/RECORD
