Metadata-Version: 2.4
Name: habemus-papadum-criu
Version: 0.7.0
Summary: Easy process freeze & thaw
Project-URL: Homepage, https://github.com/habemus-papadum/pdum_criu
Project-URL: Repository, https://github.com/habemus-papadum/pdum_criu
Project-URL: Documentation, https://github.com/habemus-papadum/pdum_criu
Author-email: Nehal Patel <nehal@alum.mit.edu>
License: MIT License
License-File: LICENSE
Classifier: Intended Audience :: Developers
Classifier: License :: OSI Approved :: MIT License
Classifier: Operating System :: OS Independent
Classifier: Programming Language :: Python :: 3
Classifier: Topic :: Software Development :: Libraries
Classifier: Topic :: Software Development :: Libraries :: Python Modules
Requires-Python: >=3.12
Requires-Dist: rich>=14.2.0
Requires-Dist: typer>=0.20.0
